{
    "faculty_details": [
        {
            "department": "S&H-Physics",
            "faculty_members": [
                {
                    "name": "MS. A K. TAMIL VATHANA",
                    "dob": "08-06-1994",
                    "date_of_joining": "07-01-2019",
                    "aicte_id": "AU1",
                    "phd_thesis_title": " ",
                    "year_of_starting": "2016",
                    "educational_qualification": [
                        {
                            "degree": "B.SC.",
                            "specialization": "PHYSICS",
                            "college_name": "RAJARATNAM COLLEGE FOR WOMEN SIVAKASI",
                            "year_of_passing": "2014"
                        },
                        {
                            "degree": "M.SC.",
                            "specialization": "PHYSICS",
                            "college_name": "ACADEMY OF HIGHER EDUCATION",
                            "year_of_passing": "2016"
                        },
                        {
                            "degree": "PHIL",
                            "specialization": "PHYSICS",
                            "college_name": "RAJARATNAM COLLEGE FOR WOMEN SIVAKASI",
                            "year_of_passing": "2017"
                        }
                    ],
                    "designation": "ASSISTANT PROFESSOR",
                    "academic_experience": [
                        {
                            "current_position": "4 Years",
                            "previous_position": "0 Years"
                        }
                    ]
                }
            ]
        },
        {
            "department": " ",
            "faculty_members": [
                {
                    "name": "MRS. M. NAJEEMA",
                    "dob": "06-04-1990",
                    "date_of_joining": "05-02-2018",
                    "aicte_id": "AU1",
                    "phd_thesis_title": " ",
                    "year_of_starting": "2014",
                    "educational_qualification": [
                        {
                            "degree": "B.SC.",
                            "specialization": "PHYSICS",
                            "college_name": "COLLEGE",
                            "year_of_passing": "2010"
                        },
                        {
                            "degree": "M.SC.",
                            "specialization": "PHYSICS",
                            "college_name": "COLLEGE",
                            "year_of_passing": "2012"
                        },
                        {
                            "degree": "M.PHIL",
                            "specialization": "PHYSICS",
                            "college_name": "COLLEGE",
                            "year_of_passing": "2014"
                        }
                    ],
                    "designation": "ASSISTANT PROFESSOR",
                    "academic_experience": [
                        {
                            "current_position": "5 Years",
                            "previous_position": "0 Years"
                        }
                    ]
                }
            ]
        }
    ]
}